renumseq/__init__.py
renumseq/__main__.py
renumseq-2.1.0.dist-info/licenses/LICENSE
renumseq-2.1.0.dist-info/METADATA
renumseq-2.1.0.dist-info/WHEEL
renumseq-2.1.0.dist-info/entry_points.txt
renumseq-2.1.0.dist-info/top_level.txt
renumseq-2.1.0.dist-info/RECORD
