Metadata-Version: 2.4
Name: renumSeq
Version: 2.1.0
Summary: Tool to renumber image sequences.
Home-page: https://github.com/jrowellfx/renumSeq
Author: James Philip Rowell
Author-email: james@alpha-eleven.com
License: BSD-3-Clause
Classifier: Programming Language :: Python :: 3
Classifier: Operating System :: POSIX
Classifier: Operating System :: Unix
Classifier: Operating System :: MacOS
Classifier: Development Status :: 5 - Production/Stable
Requires-Python: >=3.7, <4
License-File: LICENSE
Requires-Dist: seqLister>=1.2.0
Requires-Dist: lsseq>=4.0.0
Dynamic: author
Dynamic: author-email
Dynamic: classifier
Dynamic: description
Dynamic: description-content-type
Dynamic: home-page
Dynamic: license
Dynamic: license-file
Dynamic: requires-dist
Dynamic: requires-python
Dynamic: summary
